
# 文章出处

> 文章出自：[安卓进阶学习指南](https://github.com/iwannabetop/Awesome-Android-Learning-Guide)
> 
> 作者：[Struggle](https://github.com/LiPingStruggle)
> 
> 审核者: [justdoitJX](https://github.com/justdoitJX) 
>
> 完稿日期：2017.10.23

# 深入理解泛型

随着项目的深入会涉及到架构设计、以及系统源码分析的时候我们就会发现需要使用大量的泛型，当你去读别人写的源码有没有想过别人为什么这样设计？有没有更好的方案？这都是我们每个人应该思考的问题，我主要从以下几个方面来分析泛型

* 泛型是什么？

*  为什么要使用泛型？

* 泛型的实现原理？


###什么是泛型

Java1.5发行版本中增加了泛型。在没有泛型之前，从集合中读取到的每一个对象都必须进行转换。如果有人不小心插入了类型错误的对象，在编译期间是不会报错的只有在运行时会抛一个类型转换错误。有了泛型之后，可以告诉编译器每个集合中接受哪些对象类型。编译器自动地为你的插入进行转化。并在编译时告知是否插入了类型错误的对象。这样可以使程序既更加安全，也更加清楚，但是要享有这些优势有一定的难度。下面就一步一步来分析

###为什么要使用泛型

前面介绍了泛型可以在编译期间发现错误，而不用等到运行时抛出异常。
下面我们来看一个例子

```java
public class GenericityTest {

    public static void main(String args[]) {
        User u = new User("1", "Struggle");

        //没有使用泛型
        List list = new ArrayList();
        list(u, list);

        //使用泛型
        List<User> listUser = new ArrayList<>();
        listUser(u, listUser);
    }

    private static void listUser(User u, List<User> listUser) {
        listUser.add(u);
//        listUser.add("fdf"); //这里使用了泛型编译就直接不允许你添加
        for (User user : listUser) {
            System.out.println(user);
        }
    }

    private static void list(User u, List list) {
        list.add(u);
//        list.add("s"); //
        for (int i = 0; i < list.size(); i++) {
            Object object = list.get(i);
            if (object instanceof User) {
                User user = (User) object;
                System.out.println(user);
            }
        }
    }

    static class User {
        String id;
        String name;

        public User(String id, String name) {
            this.id = id;
            this.name = name;
        }

        @Override
        public String toString() {
            return "User{" +
                    "id='" + id + '\'' +
                    ", name='" + name + '\'' +
                    '}';
        }
    }
}
```

我们看上面一个简单的例子如果用
1.没有使用泛型实现会有以下几个问题
（1）在遍历的时候需要强制类型转换
（2）list方法中添加 list.add("s") 这里我添加一个String编译器不会报错而是在运行时报类型转换错误 java.lang.ClassCastException: java.lang.String cannot be cast to com.example.GenericityTest$User 防止抛出这个异常就需要判断类型
（3）防止类型转换错误就需要在list方法中加入类型判断instanceof
2.泛型实现就不需要了编译器帮我匹配到了它认为正确的类型，但是泛型也会有问题
（1）用过的小伙伴应该都知道会有一个泛型擦除的问题也就是Java并非真正的实现了泛型而是通过编译检查、匹配、擦除、桥接来实现的也叫伪泛型
泛型擦除引发的问题
看一个例子下面这个代码是别人遇到的错误，也是我在2年前做架构的时候遇到的错误当时我也有了解是泛型擦除的问题但是没有深入研究
原因是没有为泛型指定明确的类型，导致Java类型擦除异常
ArrayList<T> list = new ArrayList<T>();
list = gson.fromJson(jsonStr, new TypeToken<List<T>>() {}.getType());
但是老是出现如下异常：
java.lang.ClassCastException: com.google.gson.internal.LinkedTreeMap cannot be cast to com.example.administrator.cb.model.JobItemInfo
下面是我当时的解决方案
我将BaseReceivePacket类中的泛型改为了JSONObject提供了一个接口来实现解析操作
```java
 public class SimpleJsonResult implements  JsonResult{
     
     private Class mClass;
    
     public SimpleJsonResult(Class mClass){
       this.mClass = mClass;
     }
     
    @Override
    public BaseReceivePacket onJsonAnalysis(JSONObject object)
        throws JSONException {
      BaseReceivePacket u= null;
      Gson gson = new Gson();
      if (object != null) {
        JSONObject json = getJson(object);
        if (json != null) {
          u = (BaseReceivePacket) gson.fromJson(json.toString(),mClass);
        }
      }
      return u;
    }
        
    public JSONObject getJson(JSONObject object) {
      return object.optJSONObject("body");
    }
  }

public class BaseReceivePacket {
    
    private String code;
    private String message;
    private JSONObject object;
}
```

###泛型的实现原理

#####1.泛型擦除
看例子之前我们先来了解一下javap反编译语法
```javascript
用法: javap <options> <classes>
其中, 可能的选项包括:
  -help  --help  -?        输出此用法消息
  -version                 版本信息
  -v  -verbose             输出附加信息
  -l                       输出行号和本地变量表
  -public                  仅显示公共类和成员
  -protected               显示受保护的/公共类和成员
  -package                 显示程序包/受保护的/公共类
                           和成员 (默认)
  -p  -private             显示所有类和成员
  -c                       对代码进行反汇编
  -s                       输出内部类型签名
  -sysinfo                 显示正在处理的类的
                           系统信息 (路径, 大小, 日期, MD5 散列)
  -constants               显示最终常量
  -classpath <path>        指定查找用户类文件的位置
  -cp <path>               指定查找用户类文件的位置
  -bootclasspath <path>    覆盖引导类文件的位置
```
```java
public class TestTypeErase {
    public static void main(String []args){
        List<String> listString = new ArrayList<>();
        listString.add("Struggle");
    }
}
```

利用javap查看反编译信息
```java
➜  example javap -c  TestTypeErase.class 
Compiled from "TestTypeErase.java"
public class com.example.TestTypeErase {
  public com.example.TestTypeErase();
    Code:
       0: aload_0
       1: invokespecial #1                  // Method java/lang/Object."<init>":()V
       4: return

  public static void main(java.lang.String[]);
    Code:
       0: new           #2                  // class java/util/ArrayList
       3: dup
       4: invokespecial #3                  // Method java/util/ArrayList."<init>":()V
       7: astore_1
       8: aload_1
       9: ldc           #4                  // String Struggle
      11: invokeinterface #5,  2            // InterfaceMethod java/util/List.add:(Ljava/lang/Object;)Z
      16: pop
      17: return
}
```
我们来看11这里List.add参数是Object类型而不是String这里就说明了Java没有实现真正的泛型而是伪泛型
那么上面的类型在字节码中为什么是Object类型呢？可不可以是其它类型呢？答案是可以的下面我们来看看原始类型

#####2.有限制类型参数
```java
public class TestTypeErase {
    public static void main(String []args){
        ArrayList<Integer> listString = new ArrayList<Integer>();
        listString.add(1);
    }

   static class ArrayList<T extends Number>{
       List<T> list = new java.util.ArrayList<T>();
       void add(T t){
           list.add(t);
       }
   }
}
```

利用javap查看反编译信息
```java
➜  example  javap -c  TestTypeErase.class
Compiled from "TestTypeErase.java"
public class com.example.TestTypeErase {
  public com.example.TestTypeErase();
    Code:
       0: aload_0
       1: invokespecial #1                  // Method java/lang/Object."<init>":()V
       4: return

  public static void main(java.lang.String[]);
    Code:
       0: new           #2                  // class com/example/TestTypeErase$ArrayList
       3: dup
       4: invokespecial #3                  // Method com/example/TestTypeErase$ArrayList."<init>":()V
       7: astore_1
       8: aload_1
       9: iconst_1
      10: invokestatic  #4                  // Method java/lang/Integer.valueOf:(I)Ljava/lang/Integer;
      13: invokevirtual #5                  // Method com/example/TestTypeErase$ArrayList.add:(Ljava/lang/Number;)V
      16: return
}
➜  example  
```

我们来看13这里的原始数据类型就不是Object类型了因为我们上面使用了一种有限制类型参数也就是说上面只能添加Number的子类以及Number类型的数据添加其它类型编译器就会报错

#####3.桥接方法
先来看下面的例子
```java

public class Pair<T> {
    private T value;

    public T getValue() {
        return value;
    }

    public void setValue(T value) {
        this.value = value;
    }
}

public class DateInter extends Pair<Date> {
    @Override
    public void setValue(Date value) {
        super.setValue(value);
    }

    @Override
    public Date getValue() {
        return super.getValue();
    }
}
```
利用javap查看反编译信息

```java
➜  example javap -c DateInter.class
Compiled from "DateInter.java"
public class com.example.DateInter extends com.example.Pair<java.util.Date> {
  public com.example.DateInter();
    Code:
       0: aload_0
       1: invokespecial #1                  // Method com/example/Pair."<init>":()V
       4: return

  public void setValue(java.util.Date);
    Code:
       0: aload_0
       1: aload_1
       2: invokespecial #2                  // Method com/example/Pair.setValue:(Ljava/lang/Object;)V
       5: return

  public java.util.Date getValue();
    Code:
       0: aload_0
       1: invokespecial #3                  // Method com/example/Pair.getValue:()Ljava/lang/Object;
       4: checkcast     #4                  // class java/util/Date
       7: areturn

  public void setValue(java.lang.Object);
    Code:
       0: aload_0
       1: aload_1
       2: checkcast     #4                  // class java/util/Date
       5: invokevirtual #5                  // Method setValue:(Ljava/util/Date;)V
       8: return

  public java.lang.Object getValue();
    Code:
       0: aload_0
       1: invokevirtual #6                  // Method getValue:()Ljava/util/Date;
       4: areturn
}
```
我们来看看DateInter类有一个无参构造方法系统生成的还有4个方法是不是很奇怪？
我们下面来分析一下

这里简单的引入一些虚拟机的一些关键信息有助于我们理解
invokestatic 调用静态方法
invokespecial 调用实例构造器<init>方法、私有方法和父类方法
invokevirtual 调用所有的虚方法。
invokeinterface 调用接口方法，会在运行时再确定一个实现接口的对象
按我上面所说的擦除应该是这样
```java
public class DateInter extends Pair<Object> {
    @Override
    public void setValue(Object value) {//1
        super.setValue(value); 
    }

    @Override
    public Object getValue() { //2
        return super.getValue();
    }

}

public class Pair<Object> {
    private Object value;

    public Object getValue() {
        return value;
    }

    public void setValue(Object value) {
        this.value = value;
    }
}
```

1.分析第一个方法setValue#2很明显这里是直接调用了父类的方法注意这里参数是Object因为父类的T类型被擦除了
2.分析第二个方法getValue#3也是调用了父类的方法再来看#4做了一个checkcast检查并强制类型转换
3.分析第三个方法setValue注意参数是Object#4做了强制类型转换#5调用了自己的虚方法
4.分析第四个方法getValue#6也是调用了自己的虚方法

针对上面的分析是不是有几点疑问
1.为什么一个类可以同时出现方法名相同返回类型不同 ？
  正常这种情况是编译不过的为啥虚拟机就通过了呢？没办法Java没有真正的实现泛型只能通过重写方法来实现(为了兼容1.5以前的版本)也就是桥接方法
2.为什么我们实际使用的时候调用的是设置的T类型？
  其实就是我们上面所说的用桥接方法来实现的那么是如何实现的呢？相信你们应该看出来了
  
我们现在再来分析整个调用过程
1.第一个方法setValue(java.util.Date)#2调用了父类的 Method com/example/Pair.setValue:(Ljava/lang/Object;)V方法。
2.上面调用了父类的setValue(java/lang/Object)方法我们的子类重写(上面有解释正常是不能重写了因为java没有真正的实现泛型只能通过取巧的方式来实现了所以虚拟机就默认这样是可以重写的这个过程是虚拟机内部执行的我们可以不用关注)了父类方法。
3.接下来看子类的setValue(java.lang.Object)方法这个时候我们的参数是Object而我们传入的泛型参数是Date所以就执行了#4强制类型转换#5再调用自己的setValue这样就完美的实现了桥接。

# 总结
最后，做一个总结。本文主要围绕三个问题简单聊了聊我对泛型的理解

* 泛型是什么？
  简单理解就是可变类型
  
* 为什么要使用泛型？
  1.可以让我们提前发现错误
  2.可以设计出通用的架构
  3.可以更高效更快捷编码
  
* 泛型是实现的原理？
  1.泛型擦除 
  2.有限制类型参数（这里还有一些协变逆变之类的需要自己去了解这里就不做分析了）
  3.桥接方法
  

# Thanks

- 《Java 编程思想》
- 《Effective》第2版
- 《深入理解虚拟机》第2版 http://blog.csdn.net/u011240877/article/details/77426423
- http://blog.csdn.net/lonelyroamer/article/details/7868820
- http://blog.csdn.net/mhmyqn/article/details/47342577
- http://blog.csdn.net/ns_code/article/details/17965867
